my_package_msoyyo/__init__.py
my_package_msoyyo/hello.py
my_package_msoyyo-0.1.0.dist-info/WHEEL
my_package_msoyyo-0.1.0.dist-info/METADATA
my_package_msoyyo-0.1.0.dist-info/RECORD
